Workbook
Name Years: '[1]Value Summary'!$A$3:$A$17

Sheet Updated Multi-Year Budget
A1: Laugh CRA
A2: Multi-Year Project Area Budget Projections
A3: #VALUE!
C6: HISTORIC | D6: PROJECTED ========>
C7: Year 1 | D7: Year 2 | E7: Year 3 | F7: Year 4 | G7: Year 5 | H7: Year 6 | I7: Year 7 | J7: Year 8 | K7: Year 9 | L7: Year 10 | M7: Year 11 | N7: Year 12 | O7: Year 13 | P7: Year 14 | Q7: Year 15 | R7: Year 16 | S7: Year 17 | T7: Year 18 | U7: Year 19 | V7: Year 20 | X7: PER Shannon Wimmer, DO NOT INCLUDE TY2023/FY2024 or TY2022/FY2023. In dispute with County over whether or not they get this. Mayor decided to just not include this year. 10/30/2020.
A8: Tax Year | B8: 2023 | C8: 2024 | D8: 2025 | E8: 2026 | F8: 2027 | G8: 2028 | H8: 2029 | I8: 2030 | J8: 2031 | K8: 2032 | L8: 2033 | M8: 2034 | N8: 2035 | O8: 2036 | P8: 2037 | Q8: 2038 | R8: 2039 | S8: 2040 | T8: 2041 | U8: 2042 | V8: 2044
A9: Payment Year | B9: 2024 | C9: 2025 | D9: 2026 | E9: 2027 | F9: 2028 | G9: 2029 | H9: 2030 | I9: 2031 | J9: 2032 | K9: 2033 | L9: 2034 | M9: 2035 | N9: 2036 | O9: 2037 | P9: 2038 | Q9: 2039 | R9: 2040 | S9: 2041 | T9: 2042 | U9: 2043 | V9: 2045 | W9: TOTALS
A11: REVENUE: | AB11: 1226
A12: REVENUES
A13: TAXABLE VALUATION: | AA13: =AB13/$AB$11 -> 0.71288744 | AB13: 874 | AC13: Developed
A14: Real Property | B14: 52500000 | C14: 52500000 | D14: =C69 -> 19825000 | E14: =D14*(1+D70) -> 27450000 | F14: =E14*(1+E70) -> 27450000 | G14: =F14*(1+F70) -> 35075000 | H14: =G14*(1+G70) -> 35075000 | I14: =H14*(1+H70) -> 35075000 | J14: =I14*(1+I70) -> 35075000 | K14: =J14*(1+J70) -> 35075000 | L14: =K14*(1+K70) -> 35075000 | ... V14: =U14*(1+U70) -> 35075000 | AA14: =AB14/$AB$11 -> 0.28711256 | AB14: 352 | AC14: Undeveloped
A15: Personal Property | B15: 0 | C15: 0 | D15: 0 | E15: 0 | F15: 0 | G15: 0 | H15: 0 | I15: 0 | J15: 0 | K15: 0 | L15: 0 | M15: 0 | N15: 0 | O15: 0 | P15: 0 | Q15: 0 | R15: 0 | S15: 0 | T15: 0 | U15: 0 | V15: 0
A16: Centrally Assessed | B16: 10000000 | C16: 10000000 | D16: 10000000 | E16: 10000000 | F16: 10000000 | G16: 10000000 | H16: 10000000 | I16: 10000000 | J16: 10000000 | K16: 10000000 | L16: 10000000 | M16: 10000000 | N16: 10000000 | O16: 10000000 | P16: 10000000 | Q16: 10000000 | R16: 10000000 | S16: 10000000 | T16: 10000000 | U16: 10000000 | V16: 10000000
A17: Total Assessed Value | C17: =SUM(C14:C16) -> 12644832 | D17: =SUM(D14:D16) -> 19963117 | E17: =SUM(E14:E16) -> 27588117 | F17: =SUM(F14:F16) -> 27588117 | G17: =SUM(G14:G16) -> 35213117 | H17: =SUM(H14:H16) -> 35213117 | I17: =SUM(I14:I16) -> 35213117 | J17: =SUM(J14:J16) -> 35213117 | ... V17: =SUM(V14:V16) -> 35213117
A18: Base Year Value
A19: Real Property | B19: 5000000 | C19: =S19 -> 0
A20: Personal Property | C20: 0
A21: Centrally Assessed | C21: =S21 -> 0
A22: Base Year Value | B22: 5000000 | C22: 0 | D22: 0 | E22: 0 | F22: 0 | G22: 0 | H22: 0 | I22: 0 | J22: 0 | K22: 0 | L22: 0 | M22: 0 | N22: 0 | O22: 0 | P22: 0 | Q22: 0 | R22: 0
A23: Total Incremental Assessed Value | C23: =C17-C22 -> 12644832 | D23: =D17-D22 -> 19963117 | E23: =E17-E22 -> 27588117 | F23: =F17-F22 -> 27588117 | G23: =G17-G22 -> 35213117 | H23: =H17-H22 -> 35213117 | I23: =I17-I22 -> 35213117 | J23: =J17-J22 -> 35213117 | ... V23: =V17-V22 -> 35213117
A25: TAX RATES
A26: 1010_BEAVER | D26: 0.001519
A27: 1010_BOX ELDER | D27: 0.001218
A28: 1010_CACHE | D28: 0.001124
A29: 1010_CARBON | D29: 0.002495
A30: 1010_DAVIS | D30: 0.001034
A31: 1010_EMERY COUNTY | D31: 0.004283
A32: 1010_IRON | D32: 0.000794
A33: 1010_JUAB | D33: 0.001947
A34: 1010_KANE | D34: 0.002006
A35: 1010_MORGAN | D35: 0.001727
W36: =SUM(U36:U36) -> 0
A37: PARTICIPATION PERCENTAGES
A38: Tooele County | C38: 0.75 | D38: =C38 -> 0.75 | E38: =D38 -> 0.75 | F38: =E38 -> 0.75 | G38: =F38 -> 0.75 | H38: =G38 -> 0.75 | I38: =H38 -> 0.75 | J38: =I38 -> 0.75 | K38: =J38 -> 0.75 | ... V38: =U38 -> 0.75
A39: Tooele County School District | C39: 0.5 | D39: =C39 -> 0.5 | E39: =D39 -> 0.5 | F39: =E39 -> 0.5 | G39: =F39 -> 0.5 | H39: =G39 -> 0.5 | I39: =H39 -> 0.5 | J39: =I39 -> 0.5 | K39: =J39 -> 0.5 | ... V39: =U39 -> 0.5
A40: Tooele City | C40: 0.75 | D40: =C40 -> 0.75 | E40: =D40 -> 0.75 | F40: =E40 -> 0.75 | G40: =F40 -> 0.75 | H40: =G40 -> 0.75 | I40: =H40 -> 0.75 | J40: =I40 -> 0.75 | K40: =J40 -> 0.75 | ... V40: =U40 -> 0.75
A42: PROJECT PORTION
A43: Tooele County | C43: =C38*C32 -> 11901.948 | D43: =D38*D32 -> 14238.693 | E43: =E38*E32 -> 19677.224 | F43: =F38*F32 -> 19677.224 | G43: =G38*G32 -> 25115.756 | H43: =H38*H32 -> 25115.756 | I43: =I38*I32 -> 25115.756 | J43: =J38*J32 -> 25115.756 | ... V43: =V38*V32 -> 25115.756 | W43: =SUM(C43:V43) -> 467347.18 | X43: Total Capped Amount of $900,000
A44: Tooele County School District | C44: =C39*C33 -> 56610.913 | D44: =D39*D33 -> 66656.848 | E44: =E39*E33 -> 92116.723 | F44: =F39*F33 -> 92116.723 | G44: =G39*G33 -> 117576.6 | H44: =H39*H33 -> 117576.6 | I44: =I39*I33 -> 117576.6 | J44: =J39*J33 -> 117576.6 | ... V44: =V39*V33 -> 117576.6 | W44: =SUM(C44:V44) -> 2188726.8 | X44: Total Capped Amount of $2,500,000
A45: Tooele City | C45: =C34*C40 -> 24221.176 | D45: =D34*D40 -> 34451.349 | E45: =E34*E40 -> 47610.193 | F45: =F34*F40 -> 47610.193 | G45: =G34*G40 -> 60769.037 | H45: =H34*H40 -> 60769.037 | I45: =I34*I40 -> 60769.037 | J45: =J34*J40 -> 60769.037 | ... V45: =V34*V40 -> 60769.037 | W45: =SUM(C45:V45) -> 1126197.5 | X45: Total Capped Amount of $2,000,000
A46: Total Property Tax Increment Available to RDA | C46: =SUM(C43:C45) -> 92734.037 | D46: =SUM(D43:D45) -> 115346.89 | E46: =SUM(E43:E45) -> 159404.14 | F46: =SUM(F43:F45) -> 159404.14 | G46: =SUM(G43:G45) -> 203461.39 | H46: =SUM(H43:H45) -> 203461.39 | I46: =SUM(I43:I45) -> 203461.39 | J46: =SUM(J43:J45) -> 203461.39 | ... W46: =SUM(W43:W45) -> 3782271.4 | Y46: =SUM(#REF!) -> #REF! | Z46: =NPV(5%,#REF!) -> #REF!
A47: Interest Revenues Earned | C47: 0 | D47: 0 | E47: 0 | F47: 0 | G47: 0 | H47: 0 | I47: 0 | J47: 0 | K47: 0 | L47: 0 | M47: 0 | N47: 0 | O47: 0 | P47: 0 | Q47: 0 | R47: 0 | S47: 0 | T47: 0 | U47: 0 | V47: 0 | W47: =SUM(C47:V47) -> 0 | Y47: =SUM(#REF!) -> #REF! | Z47: =NPV(5%,#REF!) -> #REF!
A48: Total Tax Uncollected Tax Increment | C48: 0 | D48: =C48 -> 0 | E48: =D48 -> 0 | F48: =E48 -> 0 | G48: =F48 -> 0 | H48: =G48 -> 0 | I48: =H48 -> 0 | J48: =I48 -> 0 | K48: =J48 -> 0 | ... V48: =U48 -> 0 | W48: =SUM(C48:V48) -> 0 | Y48: =SUM(#REF!) -> #REF! | Z48: =NPV(5%,#REF!) -> #REF!
A49: Total Tax Increment Actually Collected and Paid | C49: =C46 -> 92734.037 | D49: =D46 -> 115346.89 | E49: =E46 -> 159404.14 | F49: =F46 -> 159404.14 | G49: =G46 -> 203461.39 | H49: =H46 -> 203461.39 | I49: =I46 -> 203461.39 | J49: =J46 -> 203461.39 | ... V49: =V46 -> 203461.39 | W49: =SUM(C49:V49) -> 3782271.4 | Y49: =SUM(#REF!) -> #REF! | Z49: =NPV(5%,#REF!) -> #REF!
A50: RDA Fund Balance | B50: 1250000 | C50: 1250000 | D50: 1250000 | E50: 1250000 | F50: 1250000 | G50: 1250000 | H50: 1250000 | I50: 1250000 | J50: 1250000 | K50: 1250000 | L50: 1250000 | M50: 1250000 | N50: 1250000 | O50: 1250000 | P50: 1250000 | Q50: 1250000 | R50: 1250000 | S50: 1250000 | T50: 1250000 | U50: 1250000 | V50: 1250000 | W50: =SUM(C50:V50) -> 2250000
A51: Total Sources of Revenue | C51: =C47+C49+C50 -> 242734.04 | D51: =D47+D49+D50 -> 265346.89 | E51: =E47+E49+E50 -> 309404.14 | F51: =F47+F49+F50 -> 309404.14 | G51: =G47+G49+G50 -> 353461.39 | H51: =H47+H49+H50 -> 353461.39 | I51: =I47+I49+I50 -> 353461.39 | J51: =J47+J49+J50 -> 353461.39 | ... V51: =V47+V49+V50 -> 203461.39 | W51: =SUM(W47:W50) -> 6032271.4 | Y51: =SUM(#REF!) -> #REF! | Z51: =NPV(5%,#REF!) -> #REF!
C52: Test Development: 150 residential units, 50,000 sq ft commercial space, 25,000 sq ft industrial. Recent developments include new shopping center and residential complex. | W52: =SUM(U52:U52) -> 0 | AM52: COMBINED BUDGET - ALL PROJECT AREAS
C53: Major mixed-use development with residential, commercial, and retail components. Infrastructure improvements completed including roads, utilities, and public spaces.
A54: EXPENDITURES | C54: Infrastructure improvements, public facilities, economic development incentives, and administrative costs. | AM54: ACTUAL | AN54: PROJECTIONS
AN55: REMAINING LIFE
A56: PROJECT AREA BUDGET AND USE OF FUNDS | C56: Development plan implementation on schedule. All phases completed as planned with strong community support and economic impact. | AM56: TY 2018/FY 2019 TOTALS | AN56: (INCLUDES FY 2019 TOTALS)
A57: CRA Administration @ 5% | C57: No significant issues to report. Project proceeding as expected. | D57: =D49*0.05 -> 5767.3445 | E57: =E49*0.05 -> 7970.207 | F57: =F49*0.05 -> 7970.207 | G57: =G49*0.05 -> 10173.07 | H57: =H49*0.05 -> 10173.07 | I57: =I49*0.05 -> 10173.07 | J57: =J49*0.05 -> 10173.07 | K57: =K49*0.05 -> 10173.07 | ... V57: =V49*0.05 -> 10173.07 | W57: =SUM(C57:V57) -> 189113.57 | Y57: =SUM(#REF!) -> #REF! | Z57: =NPV(5%,#REF!) -> #REF!
A58: CRA Housing Requirement @ 20% | B58: 150000 | C58: 150000 | D58: 150000 | E58: 150000 | F58: 150000 | G58: 150000 | H58: 150000 | I58: 150000 | J58: 150000 | K58: 150000 | L58: 150000 | M58: 150000 | N58: 150000 | O58: 150000 | P58: 150000 | Q58: 150000 | R58: 150000 | S58: 150000 | T58: 150000 | U58: 150000 | V58: 150000 | W58: =SUM(C58:V58) -> 0 | Y58: =SUM(#REF!) -> #REF! | Z58: =NPV(5%,#REF!) -> #REF! | AM58: 3150000 | AN58: 3150000
A59: Guaranteed Developer Payment | B59: 150000 | C59: 150000 | D59: 150000 | E59: 150000 | F59: 150000 | G59: 150000 | H59: 150000 | I59: 150000 | J59: 150000 | K59: 150000 | L59: 150000 | M59: 150000 | N59: 150000 | O59: 150000 | P59: 150000 | Q59: 0 | R59: 0 | S59: 0 | T59: 0 | U59: 0 | V59: 0 | W59: 2250000 | X59: Guaranteed annual payment of $150,000 for 15 years regardless of tax increment collections. In addition to 95%?
A60: Developer Reimbursement @ 95% | C60: =C49*0.95 -> 88097.335 | D60: =D49*0.95 -> 109579.55 | E60: =E49*0.95 -> 151433.93 | F60: =F49*0.95 -> 151433.93 | G60: =G49*0.95 -> 193288.32 | H60: =H49*0.95 -> 193288.32 | I60: =I49*0.95 -> 193288.32 | J60: =J49*0.95 -> 193288.32 | ... V60: =V49*0.95 -> 193288.32 | W60: =SUM(C60:V60) -> 3593157.9 | X60: Reimbursement 95% | Cap $4,754,000 | Developer reimbursed at 95% of increment until cap is met. | Y60: =SUM(#REF!) -> #REF! | Z60: =NPV(5%,#REF!) -> #REF!
A61: Total Expenditures | C61: =SUM(C57:C60) -> 242734.04 | D61: =SUM(D57:D60) -> 265346.89 | E61: =SUM(E57:E60) -> 309404.14 | F61: =SUM(F57:F60) -> 309404.14 | G61: =SUM(G57:G60) -> 353461.39 | H61: =SUM(H57:H60) -> 353461.39 | I61: =SUM(I57:I60) -> 353461.39 | J61: =SUM(J57:J60) -> 353461.39 | ... W61: =SUM(W57:W60) -> 6032271.4 | X61: Annual Developer payment of 95% of tax increment. | Y61: =SUM(#REF!) -> #REF! | Z61: =NPV(5%,#REF!) -> #REF! | AM61: 0 | AN61: 0
AM62: 5566 | AN62: 33396
A63: RETAINED PORTION OF TAX INCREMENT | AM63: =SUM(AM58:AM62) -> 125170 | AN63: =SUM(AN58:AN62) -> 153000
A64: Tooele County | C64: =C32-C43 -> 3967.316 | D64: =D32-D43 -> 4746.2311 | E64: =E32-E43 -> 6559.0748 | F64: =F32-F43 -> 6559.0748 | G64: =G32-G43 -> 8371.9186 | H64: =H32-H43 -> 8371.9186 | I64: =I32-I43 -> 8371.9186 | J64: =J32-J43 -> 8371.9186 | ... V64: =V32-V43 -> 8371.9186 | W64: =SUM(C64:V64) -> 155782.39 | Y64: =SUM(#REF!) -> #REF! | Z64: =NPV(5%,#REF!) -> #REF! | AN64: REMAINING LIFE
A65: Tooele County School District | C65: =C33-C44 -> 56610.913 | D65: =D33-D44 -> 66656.848 | E65: =E33-E44 -> 92116.723 | F65: =F33-F44 -> 92116.723 | G65: =G33-G44 -> 117576.6 | H65: =H33-H44 -> 117576.6 | I65: =I33-I44 -> 117576.6 | J65: =J33-J44 -> 117576.6 | ... V65: =V33-V44 -> 117576.6 | W65: =SUM(C65:V65) -> 2188726.8 | Y65: =SUM(#REF!) -> #REF! | Z65: =NPV(5%,#REF!) -> #REF! | AM65: FY 2019 TOTALS | AN65: (INCLUDES 2019 TOTALS)
A66: Tooele City | C66: =C34-C45 -> 8073.7252 | D66: =D34-D45 -> 11483.783 | E66: =E34-E45 -> 15870.064 | F66: =F34-F45 -> 15870.064 | G66: =G34-G45 -> 20256.346 | H66: =H34-H45 -> 20256.346 | I66: =I34-I45 -> 20256.346 | J66: =J34-J45 -> 20256.346 | ... V66: =V34-V45 -> 20256.346 | W66: =SUM(C66:V66) -> 375399.17 | Y66: =SUM(#REF!) -> #REF! | Z66: =NPV(5%,#REF!) -> #REF!
W67: =SUM(W61:W66) -> 8752179.8 | AM67: 119604 | AN67: 119604
C68: Original budget shows these values, which include residential | W68: =W67-W59 -> 6502179.8 | AM68: 2293684 | AN68: 13608233
B69: 52500000 | C69: 52500000 | D69: 52500000 | E69: 54600000 | F69: 56238000 | G69: 57925140 | H69: 59662894 | I69: 61452781 | J69: 63296364 | K69: 65195255 | L69: 68455018 | M69: 71877769 | N69: 75471658 | O69: 79245240 | P69: 83207502 | Q69: 87367878 | R69: 91736271 | S69: 96323085 | T69: 101139239 | U69: 106196201 | V69: 117081312 | AM69: =SUM(AM67:AM68) -> 2413288 | AN69: =SUM(AN67:AN68) -> 13727837
D70: =(D69-C69)/C69 -> 0.38461538 | E70: =(E69-D69)/D69 -> 0 | F70: =(F69-E69)/E69 -> 0.27777778 | G70: =(G69-F69)/F69 -> 0 | H70: =(H69-G69)/G69 -> 0 | I70: =(I69-H69)/H69 -> 0 | J70: =(J69-I69)/I69 -> 0 | K70: =(K69-J69)/J69 -> 0 | ... V70: =(V69-U69)/U69 -> 0
C73: 1 | D73: 2 | E73: 3 | F73: 4 | G73: 5 | H73: 6 | I73: 7 | J73: 8 | K73: 9 | L73: 10 | M73: 11 | N73: 12 | O73: 13 | P73: 14 | Q73: 15 | R73: 16 | S73: 17 | T73: 18 | U73: 19 | V73: 20
A74: CALCULATIONS FOR REPORT
A76: Relative Growth in Assessed Values
A77: Project Area
A78: Current Year Assessed Value | C78: =C17 -> 12644832 | S78: =S17 -> 35213117 | T78: =T17 -> 35213117 | U78: =U17 -> 35213117
A79: Prior Year Assessed Value | B79: =C22 -> 0 | C79: =#REF! -> #REF! | S79: =C17 -> 12644832 | T79: =S17 -> 35213117 | U79: =T17 -> 35213117
A80: Annual Growth Rate | C80: =(C78-C79)/C79 -> #REF! | S80: =(S78-S79)/S79 -> 1.7847833 | T80: =(T78-T79)/T79 -> 0 | U80: =(U78-U79)/U79 -> 0
A81: Lifetime Growth Rate each year | C81: =(C78-$B$79)/$B$79 -> #DIV/0! | S81: =(S78-$B$79)/$B$79 -> #DIV/0! | T81: =(T78-$B$79)/$B$79 -> #DIV/0! | U81: =(U78-$B$79)/$B$79 -> #DIV/0!
A82: AAGR | C82: =(C78/$B$79)^(1/C93)-1 -> #DIV/0! | S82: =(S78/$B$79)^(1/S93)-1 -> #DIV/0! | T82: =(T78/$B$79)^(1/T93)-1 -> #DIV/0! | U82: =(U78/$B$79)^(1/U93)-1 -> #DIV/0!
A83: CAGR | C83: =(C78/$B$79)^(1/C93)-1 -> #DIV/0! | S83: =(S78/$B$79)^(1/S93)-1 -> #DIV/0! | T83: =(T78/$B$79)^(1/T93)-1 -> #DIV/0! | U83: =(U78/$B$79)^(1/U93)-1 -> #DIV/0!
A85: Tooele City
A86: Current Year Assessed Value | B86: 1997 | C86: 1204580532 | S86: 1466339474 | T86: 1576891710 | U86: 1782491357
A87: Prior Year Assessed Value | B87: 1190576948 | C87: =#REF! -> #REF! | S87: =C86 -> 1204580532 | T87: =S86 -> 1466339474 | U87: =T86 -> 1576891710
A88: Annual Growth Rate | C88: =(C86-C87)/C87 -> #REF! | S88: =(S86-S87)/S87 -> 0.21730298 | T88: =(T86-T87)/T87 -> 0.075393344 | U88: =(U86-U87)/U87 -> 0.13038286
A89: Lifetime Growth Rate each year | C89: =(C86-$B$87)/$B$87 -> 0.011762015 | S89: =(S86-$B$87)/$B$87 -> 0.23162092 | T89: =(T86-$B$87)/$B$87 -> 0.32447694 | U89: =(U86-$B$87)/$B$87 -> 0.49716603
A90: AAGR | C90: =(C86/$B$87)^(1/C93)-1 -> 0.00058483996 | S90: =(S86/$B$87)^(1/S93)-1 -> 0.0099699012 | T90: =(T86/$B$87)^(1/T93)-1 -> 0.012855458 | U90: =(U86/$B$87)^(1/U93)-1 -> 0.017701543
A91: CAGR | V91: =SUM(C91:U91) -> 0
A93: # Years since base | C93: =S93-1 -> 20 | S93: =T93-1 -> 21 | T93: =2019-1997 -> 22 | U93: =2020-1997 -> 23 | V93: =SUM(C93:U93) -> 86
A95: Growth in Tax Increment
A96: Tax Increment from Project Area
A97: Annual Actual Revenues | C97: =C35 -> 161385.99 | S97: =S35 -> 349666.25 | T97: =T35 -> 349666.25 | U97: =U35 -> 349666.25
A98: Annual Base Year Value Revenues | C98: =((C19+C21)*(C26+C28+C27))+((C20)*(#REF!+#REF!+#REF!)) -> #REF! | S98: =((S19+S21)*(S26+S28+S27))+((S20)*(C26+C28+C27)) -> 0 | T98: =((T19+T21)*(T26+T28+T27))+((T20)*(S26+S28+S27)) -> 0 | U98: =((U19+U21)*(U26+U28+U27))+((U20)*(T26+T28+T27)) -> 0
A99: Lifetime Actual Revenues | C99: =SUM($C$35:C35) -> 161385.99 | S99: =SUM($C$35:S35) -> 5453181 | T99: =SUM($C$35:T35) -> 5802847.3 | U99: =SUM($C$35:U35) -> 6152513.5
A100: Lifetime Base Year Value Revenues | C100: =SUM($C$98:C98) -> #REF! | S100: =SUM($C$98:S98) -> #REF! | T100: =SUM($C$98:T98) -> #REF! | U100: =SUM($C$98:U98) -> #REF!
A101: Annual % Above Base | C101: =C97/C98 -> #REF! | S101: =S97/S98 -> #DIV/0! | T101: =T97/T98 -> #DIV/0! | U101: =U97/U98 -> #DIV/0!
A102: Lifetime % Above Base | C102: =C99/C100 -> #REF! | S102: =S99/S100 -> #REF! | T102: =T99/T100 -> #REF! | U102: =U99/U100 -> #REF!
A104: Pass Thru Increment (above base)
A105: Annual Actual Revenues | C105: =C35-C46 -> 68651.954 | S105: =S35-S46 -> 146204.86 | T105: =T35-T46 -> 146204.86 | U105: =U35-U46 -> 146204.86
A106: Annual Base Year Value Revenues | C106: =C98 -> #REF! | S106: =S98 -> 0 | T106: =T98 -> 0 | U106: =U98 -> 0
A107: Lifetime Actual Revenues | C107: =SUM($C$64:C66) -> 68651.954 | S107: =SUM($C$64:S66) -> 2281293.7 | T107: =SUM($C$64:T66) -> 2427498.6 | U107: =SUM($C$64:U66) -> 2573703.5
A108: Lifetime Base Year Value Revenues | C108: =C100 -> #REF! | S108: =S100 -> #REF! | T108: =T100 -> #REF! | U108: =U100 -> #REF!
A109: Annual % Above Base | C109: =(C105-C106)/C106 -> #REF! | S109: =(S105-S106)/S106 -> #DIV/0! | T109: =(T105-T106)/T106 -> #DIV/0! | U109: =(U105-U106)/U106 -> #DIV/0!
A110: Lifetime % Above Base | C110: =(C107-C108)/C108 -> #REF! | S110: =(S107-S108)/S108 -> #REF! | T110: =(T107-T108)/T108 -> #REF! | U110: =(U107-U108)/U108 -> #REF!
G118: =I104857 -> 0
C120: =-C20*C29 -> 0 | S120: =-S20*S29 -> 0 | T120: =-T20*T29 -> 0 | U120: =-U20*U29 -> 0 | W120: =SUM(C120:V120) -> 0
...

Sheet Sheet1
C6: GROWTH IN ASSESSED VALUE | E6: CURRENT YEAR | F6: COMPARISON YEAR | G6: GROWTH RATE | H6: CAGR
C8: ASSESSED VALUES IN PROJECT AREA
C9: Annual Growth in Project Area (2024 vs. 2023) | E9: ='Updated Multi-Year Budget'!C23 -> 12644832 | F9: N/A | G9: N/A | H9: N/A
C10: Life Growth in Project Area (2024 vs. Base) | E10: =E9 -> 12644832 | F10: =F9 -> N/A | G10: =G9 -> N/A | H10: =H9 -> N/A
C17: GROWTH IN TAX INCREMENT | E17: ORIGINAL BUDGET* REVENUES | F17: ACTUAL REVENUE | G17: BASE YEAR VALUE REVENUES | H17: %
H18: ABOVE
H19: BASE
C20: TAX INCREMENT FROM PROJECT AREA
C21: Tax Year 2024 | E21: 15691.616 | F21: =#REF! -> #REF! | G21: =($C$14*-1)*#REF! -> #REF! | H21: =(F21-G21)/G21 -> #REF!
C22: Lifetime Revenue (2017-2026) | E22: =#REF! -> #REF! | F22: =SUM(#REF!) -> #REF! | G22: =#REF! -> #REF! | H22: =(F22-G22)/G22 -> #REF!
C23: PASS THROUGH INCREMENT (ABOVE BASE)
C24: Tax Year 2024 | E24: =E21 -> 15691.616 | F24: =F21 -> #REF! | G24: =G21 -> #REF! | H24: =(F24-G24)/G24 -> #REF!
C25: Lifetime Revenue (2017-2026) | E25: =E22 -> #REF! | F25: =F22 -> #REF! | G25: =G22 -> #REF! | H25: =(F25-G25)/G25 -> #REF!
C29: PROJECT AREA BUDGET | D29: FY 2025-2045
C30: REVENUES | D30: TOTALS | E30: Totals
C31: Property Tax Increment | D31: =SUM(#REF!) -> #REF! | E31: =SUM('Updated Multi-Year Budget'!C51:V51) -> 6032271.4
C32: Total Revenue | D32: =SUM(D31) -> #REF! | E32: =SUM(E31) -> 6032271.4
C33: EXPENDITURES | D33: TOTALS | E33: Totals
C34: CRA Administration @ 5% | D34: =SUM(#REF!) -> #REF! | E34: =SUM('Updated Multi-Year Budget'!C57:V57) -> 189113.57
C35: Guaranteed Developer Payment | D35: =SUM(#REF!)-1 -> #REF! | E35: =SUM('Updated Multi-Year Budget'!C59:V59) -> 2250000
C36: Developer Reimbursment | E36: =SUM('Updated Multi-Year Budget'!C60:V60) -> 3593157.9
C37: Total Expenditures | D37: =SUM(D34:D35) -> #REF! | E37: =SUM(E34:E36) -> 6032271.4

Sheet Annual Budget
A1: 1000 North Retail Community Reinvestment Area | H1: 1000 North Retail Community Reinvestment Area | L1: 1000 North Retail Community Reinvestment Area
A2: =C6&" Annual Budget" -> 2025 Annual Budget | H2: =J6&" Annual Budget" -> 2026 Annual Budget | L2: =N6&" Annual Budget" -> 2027 Annual Budget
A3: #VALUE! | H3: #VALUE! | L3: #VALUE!
B4: Year | C4: =LOOKUP(C5,'Updated Multi-Year Budget'!C8:V8,'Updated Multi-Year Budget'!C73:V73) -> 1 | I4: Year | J4: 2 | M4: Year | N4: 3
B5: Tax Year | C5: 2024 | I5: Tax Year | J5: 2025 | M5: Tax Year | N5: 2026
B6: Payment Year | C6: =LOOKUP(C5,'Updated Multi-Year Budget'!C8:V8,'Updated Multi-Year Budget'!C9:V9) -> 2025 | I6: Payment Year | J6: 2026 | M6: Payment Year | N6: 2027
A7: REVENUES | H7: REVENUES | L7: REVENUES
A8: TAXABLE VALUATION: | H8: TAXABLE VALUATION: | L8: TAXABLE VALUATION:
A9: Real Property | C9: ='Updated Multi-Year Budget'!C14 -> 12506715 | H9: Real Property | J9: ='Updated Multi-Year Budget'!D14 -> 19825000 | L9: Real Property | N9: ='Updated Multi-Year Budget'!E14 -> 27450000
A10: Personal Property | C10: =LOOKUP($C$5,'Updated Multi-Year Budget'!$C$8:$V$8,'Updated Multi-Year Budget'!C15:V15) -> 0 | H10: Personal Property | J10: =LOOKUP($C$5,'Updated Multi-Year Budget'!$C$8:$V$8,'Updated Multi-Year Budget'!J15:AC15) -> 0 | L10: Personal Property | N10: =LOOKUP($C$5,'Updated Multi-Year Budget'!$C$8:$V$8,'Updated Multi-Year Budget'!N15:AG15) -> 0
A11: Centrally Assessed | C11: ='Updated Multi-Year Budget'!C16 -> 138117 | H11: Centrally Assessed | J11: ='Updated Multi-Year Budget'!C16 -> 138117 | L11: Centrally Assessed | N11: ='Updated Multi-Year Budget'!E16 -> 138117
A12: Total Assessed Value | C12: =LOOKUP($C$5,'Updated Multi-Year Budget'!$C$8:$V$8,'Updated Multi-Year Budget'!C17:V17) -> 12644832 | H12: Total Assessed Value | J12: =SUM(J9:J11) -> 19963117 | L12: Total Assessed Value | N12: =SUM(N9:N11) -> 27588117
A13: Base Year Value | C13: =LOOKUP($C$5,'Updated Multi-Year Budget'!$C$8:$V$8,'Updated Multi-Year Budget'!C22:V22) -> 0 | H13: Base Year Value | J13: =LOOKUP($C$5,'Updated Multi-Year Budget'!$C$8:$V$8,'Updated Multi-Year Budget'!J22:AC22) -> 0 | L13: Base Year Value | N13: =LOOKUP($C$5,'Updated Multi-Year Budget'!$C$8:$V$8,'Updated Multi-Year Budget'!N22:AG22) -> 0
A14: Total Incremental Assessed Value | C14: =C12-C13 -> 12644832 | H14: Total Incremental Assessed Value | J14: =J12-J13 -> 19963117 | L14: Total Incremental Assessed Value | N14: =N12-N13 -> 27588117
A15: TAX RATES | C15: Real & Centrally Assessed | H15: TAX RATES | J15: Real & Centrally Assessed | L15: TAX RATES | N15: Real & Centrally Assessed
A16: ='Updated Multi-Year Budget'!A26 -> Tooele County | C16: =LOOKUP($C$5,'Updated Multi-Year Budget'!$C$8:$V$8,'Updated Multi-Year Budget'!C26:V26) -> 0.001255 | H16: Tooele County | J16: =LOOKUP($C$5,'Updated Multi-Year Budget'!$C$8:$V$8,'Updated Multi-Year Budget'!J26:AC26) -> 0.000951 | L16: Tooele County | N16: =LOOKUP($C$5,'Updated Multi-Year Budget'!$C$8:$V$8,'Updated Multi-Year Budget'!N26:AG26) -> 0.000951
A17: ='Updated Multi-Year Budget'!A27 -> Tooele County School District | C17: =LOOKUP($C$5,'Updated Multi-Year Budget'!$C$8:$V$8,'Updated Multi-Year Budget'!C27:V27) -> 0.008954 | H17: Tooele County School District | J17: =LOOKUP($C$5,'Updated Multi-Year Budget'!$C$8:$V$8,'Updated Multi-Year Budget'!J27:AC27) -> 0.006678 | L17: Tooele County School District | N17: =LOOKUP($C$5,'Updated Multi-Year Budget'!$C$8:$V$8,'Updated Multi-Year Budget'!N27:AG27) -> 0.006678
A18: ='Updated Multi-Year Budget'!A28 -> Tooele City | C18: =LOOKUP($C$5,'Updated Multi-Year Budget'!$C$8:$V$8,'Updated Multi-Year Budget'!C28:V28) -> 0.002554 | H18: Tooele City | J18: =LOOKUP($C$5,'Updated Multi-Year Budget'!$C$8:$V$8,'Updated Multi-Year Budget'!J28:AC28) -> 0.002301 | L18: Tooele City | N18: =LOOKUP($C$5,'Updated Multi-Year Budget'!$C$8:$V$8,'Updated Multi-Year Budget'!N28:AG28) -> 0.002301
A19: Total Tax Rate | C19: =C16+C18+C17 -> 0.012763 | H19: Total Tax Rate | J19: =J16+J18+J17 -> 0.00993 | L19: Total Tax Rate | N19: =N16+N18+N17 -> 0.00993
A20: PROPERTY TAX INCREMENT REVENUES | H20: PROPERTY TAX INCREMENT REVENUES | L20: PROPERTY TAX INCREMENT REVENUES
A21: =A16 -> Tooele County | C21: ='Updated Multi-Year Budget'!C32 -> 15869.264 | H21: Tooele County | J21: ='Updated Multi-Year Budget'!D32 -> 18984.924 | L21: Tooele County | N21: ='Updated Multi-Year Budget'!E32 -> 26236.299
A22: =A17 -> Tooele County School District | C22: ='Updated Multi-Year Budget'!C33 -> 113221.83 | H22: Tooele County School District | J22: ='Updated Multi-Year Budget'!D33 -> 133313.7 | L22: Tooele County School District | N22: ='Updated Multi-Year Budget'!E33 -> 184233.45
A23: =A18 -> Tooele City | C23: ='Updated Multi-Year Budget'!C34 -> 32294.901 | H23: Tooele City | J23: ='Updated Multi-Year Budget'!D34 -> 45935.132 | L23: Tooele City | N23: ='Updated Multi-Year Budget'!E34 -> 63480.257
A24: Total Property Tax Increment | C24: =LOOKUP($C$5,'Updated Multi-Year Budget'!$C$8:$V$8,'Updated Multi-Year Budget'!C35:V35) -> 161385.99 | H24: Total Property Tax Increment | J24: =SUM(J21:J23) -> 198233.75 | L24: Total Property Tax Increment | N24: =SUM(N21:N23) -> 273950
A25: PARTICIPATION PERCENTAGES | H25: PARTICIPATION PERCENTAGES | L25: PARTICIPATION PERCENTAGES
A26: Tooele County | C26: ='Updated Multi-Year Budget'!C38 -> 0.75 | H26: Tooele County | J26: ='Updated Multi-Year Budget'!J38 -> 0.75 | L26: Tooele County | N26: ='Updated Multi-Year Budget'!N38 -> 0.75
A27: Tooele County School District | C27: ='Updated Multi-Year Budget'!C39 -> 0.5 | H27: Tooele County School District | J27: ='Updated Multi-Year Budget'!J39 -> 0.5 | L27: Tooele County School District | N27: ='Updated Multi-Year Budget'!N39 -> 0.5
A28: Tooele City | C28: ='Updated Multi-Year Budget'!C40 -> 0.75 | H28: Tooele City | J28: ='Updated Multi-Year Budget'!J40 -> 0.75 | L28: Tooele City | N28: ='Updated Multi-Year Budget'!N40 -> 0.75
A30: PROJECT PORTION | H30: PROJECT PORTION | L30: PROJECT PORTION
A31: =A21 -> Tooele County | C31: ='Updated Multi-Year Budget'!C43 -> 11901.948 | H31: =H21 -> Tooele County | J31: ='Updated Multi-Year Budget'!C43 -> 11901.948 | L31: =L21 -> Tooele County | N31: ='Updated Multi-Year Budget'!E43 -> 19677.224
A32: =A22 -> Tooele County School District | C32: ='Updated Multi-Year Budget'!C44 -> 56610.913 | H32: =H22 -> Tooele County School District | J32: ='Updated Multi-Year Budget'!C44 -> 56610.913 | L32: =L22 -> Tooele County School District | N32: ='Updated Multi-Year Budget'!E44 -> 92116.723
A33: =A23 -> Tooele City | C33: ='Updated Multi-Year Budget'!C45 -> 24221.176 | H33: =H23 -> Tooele City | J33: ='Updated Multi-Year Budget'!C45 -> 24221.176 | L33: =L23 -> Tooele City | N33: ='Updated Multi-Year Budget'!E45 -> 47610.193
A34: Total Property Tax Increment Revenue to Project Area | C34: =SUM(C31:C33) -> 92734.037 | H34: Total Property Tax Increment Revenue to Project Area | J34: =SUM(J31:J33) -> 92734.037 | L34: Total Property Tax Increment Revenue to Project Area | N34: =SUM(N31:N33) -> 159404.14
A35: ='Updated Multi-Year Budget'!A47 -> Interest Revenues Earned | C35: =LOOKUP($C$5,'Updated Multi-Year Budget'!$C$8:$V$8,'Updated Multi-Year Budget'!C47:V47) -> 0 | H35: Interest Revenues Earned | J35: =LOOKUP($C$5,'Updated Multi-Year Budget'!$C$8:$V$8,'Updated Multi-Year Budget'!J47:AC47) -> 0 | L35: Interest Revenues Earned | N35: =LOOKUP($C$5,'Updated Multi-Year Budget'!$C$8:$V$8,'Updated Multi-Year Budget'!N47:AG47) -> 0
A36: ='Updated Multi-Year Budget'!A48 -> Total Tax Uncollected Tax Increment | C36: =LOOKUP($C$5,'Updated Multi-Year Budget'!$C$8:$V$8,'Updated Multi-Year Budget'!C48:V48) -> 0 | H36: Total Tax Uncollected and Paid | J36: =LOOKUP($C$5,'Updated Multi-Year Budget'!$C$8:$V$8,'Updated Multi-Year Budget'!J48:AC48) -> 0 | L36: Total Tax Uncollected and Paid | N36: =LOOKUP($C$5,'Updated Multi-Year Budget'!$C$8:$V$8,'Updated Multi-Year Budget'!N48:AG48) -> 0
A37: ='Updated Multi-Year Budget'!A49 -> Total Tax Increment Actually Collected and Paid | C37: =LOOKUP($C$5,'Updated Multi-Year Budget'!$C$8:$V$8,'Updated Multi-Year Budget'!C49:V49) -> 92734.037 | H37: Total Tax Increment Actually Collected and Paid | J37: ='Updated Multi-Year Budget'!D49 -> 115346.89 | L37: Total Tax Increment Actually Collected and Paid | N37: ='Updated Multi-Year Budget'!E49 -> 159404.14
A38: RDA Fund Balance | C38: =LOOKUP($C$5,'Updated Multi-Year Budget'!$C$8:$V$8,'Updated Multi-Year Budget'!C50:V50) -> 150000 | H38: RDA Fund Balance | J38: ='Updated Multi-Year Budget'!D50 -> 150000 | L38: RDA Fund Balance | N38: =LOOKUP($C$5,'Updated Multi-Year Budget'!$C$8:$V$8,'Updated Multi-Year Budget'!N50:AG50) -> 150000
A39: Total Sources of Revenue | C39: =LOOKUP($C$5,'Updated Multi-Year Budget'!$C$8:$V$8,'Updated Multi-Year Budget'!C51:V51) -> 242734.04 | H39: Total Sources of Revenue | J39: =SUM(J35:J38) -> 265346.89 | L39: Total Sources of Revenue | N39: =SUM(N37:N38) -> 309404.14
A41: EXPENDITURES | H41: EXPENDITURES | L41: EXPENDITURES
A42: PROJECT AREA BUDGET AND USE OF FUNDS | H42: PROJECT AREA BUDGET AND USE OF FUNDS | L42: PROJECT AREA BUDGET AND USE OF FUNDS
A43: CRA Administration @ 5% | C43: =LOOKUP($C$5,'Updated Multi-Year Budget'!$C$8:$V$8,'Updated Multi-Year Budget'!C57:V57) -> 4636.7018 | H43: CRA Administration @ 5% | J43: ='Updated Multi-Year Budget'!D57 -> 5767.3445 | L43: CRA Administration @ 5% | N43: ='Updated Multi-Year Budget'!E57 -> 7970.207
A44: CRA Housing Requirement @ 20% | C44: =LOOKUP($C$5,'Updated Multi-Year Budget'!$C$9:$V$9,'Updated Multi-Year Budget'!C58:V58) -> #N/A | H44: CRA Housing Requirement @ 20% | J44: ='Updated Multi-Year Budget'!D58 -> 0 | L44: CRA Housing Requirement @ 20% | N44: ='Updated Multi-Year Budget'!E58 -> 0
A45: Guaranteed Developer Payment | C45: =LOOKUP($C$5,'Updated Multi-Year Budget'!$C$8:$V$8,'Updated Multi-Year Budget'!C59:V59) -> 150000 | H45: Guaranteed Developer Payment | J45: ='Updated Multi-Year Budget'!D59 -> 150000 | L45: Guaranteed Developer Payment | N45: ='Updated Multi-Year Budget'!E59 -> 150000
A46: Developer Reimbursement @ 95% | C46: =LOOKUP($C$5,'Updated Multi-Year Budget'!$C$8:$V$8,'Updated Multi-Year Budget'!C60:V60) -> 88097.335 | H46: Developer Reimbursement @ 95% | J46: ='Updated Multi-Year Budget'!D60 -> 109579.55 | L46: Developer Reimbursement @ 95% | N46: ='Updated Multi-Year Budget'!E60 -> 151433.93
A47: Total Expenditures | C47: =LOOKUP($C$5,'Updated Multi-Year Budget'!$C$8:$V$8,'Updated Multi-Year Budget'!C61:V61) -> 242734.04 | H47: Total Expenditures | J47: =SUM(J43:J46) -> 265346.89 | L47: Total Expenditures | N47: =SUM(N43:N46) -> 309404.14
A49: RETAINED PORTION OF TAX INCREMENT | H49: RETAINED PORTION OF TAX INCREMENT | L49: RETAINED PORTION OF TAX INCREMENT
A50: Tooele County | C50: =LOOKUP($C$5,'Updated Multi-Year Budget'!$C$8:$V$8,'Updated Multi-Year Budget'!C64:V64) -> 3967.316 | H50: Tooele County | J50: ='Updated Multi-Year Budget'!D64 -> 4746.2311 | L50: Tooele County | N50: ='Updated Multi-Year Budget'!E64 -> 6559.0748
A51: Tooele County School District | C51: =LOOKUP($C$5,'Updated Multi-Year Budget'!$C$8:$V$8,'Updated Multi-Year Budget'!C65:V65) -> 56610.913 | H51: Tooele County School District | J51: ='Updated Multi-Year Budget'!D65 -> 66656.848 | L51: Tooele County School District | N51: ='Updated Multi-Year Budget'!E65 -> 92116.723
A52: Tooele City | C52: =LOOKUP($C$5,'Updated Multi-Year Budget'!$C$8:$V$8,'Updated Multi-Year Budget'!C66:V66) -> 8073.7252 | H52: Tooele City | J52: ='Updated Multi-Year Budget'!D66 -> 11483.783 | L52: Tooele City | N52: ='Updated Multi-Year Budget'!E66 -> 15870.064

Sheet Acreage
B2: Tax Year | C2: 2018 | D2: 2019 | E2: 2020
B3: Payment Year | C3: 2019 | D3: 2020 | E3: 2021
B4: Developed | C4: 85 | D4: =C4+D26 -> 951.6 | E4: =D4+E26 -> 966.78
B5: Undeveloped | C5: 40 | D5: =D6-D4 -> 274.4 | E5: =E6-E4 -> 259.22
B6: Total Acres | C6: 125 | D6: =C6 -> 1226 | E6: =D6 -> 1226
B7: % Developed | C7: 0.68 | D7: =D4/D6 -> 0.77618271 | E7: =E4/E6 -> 0.78856444
B8: % Undeveloped | C8: 0.32 | D8: =D5/D6 -> 0.22381729 | E8: =E5/E6 -> 0.21143556
C9: 60
C10: 150
D14: 2019 | E14: 2020 | F14: =E14+1 -> 2021
B15: New Development | D15: 2020 | E15: 2021 | F15: =E15+1 -> 2022
D16: 5.5 | E16: =6.88+8.3 -> 15.18
D17: 72.1
B26: New Dev Total | D26: =SUM(D16:D25) -> 77.6 | E26: =SUM(E16:E25) -> 15.18 | F26: =SUM(F16:F25) -> 0 | G26: =SUM(G16:G25) -> 0 | H26: =SUM(H16:H25) -> 0 | I26: =SUM(I16:I25) -> 0 | J26: =SUM(J16:J25) -> 0
